ula.sv
module ula(
    input logic[3:0] a, b,
    input logic[2:0] op,
    output logic[3:0] r,
    output logic zero
);

always_comb begin
    case(op)
        3'b000: r = a + b;
        3'b001: r = a - b;
        3'b010: r = a & b;
        3'b011: r = a | b;
        3'b100: r = a ^ b;
        3'b101: r = (a == b) ? 4'b0001 : 4'b0000;
        default: r = 4'b000;
    endcase
end

assign zero = (r == 0);
endmodule

tb_ula.sv
module tb_ula;

    // Sinais para conectar à ULA
    logic [3:0] a, b;
    logic [2:0] op;
    logic [3:0] r;
    logic zero;

    // Instancia o módulo ULA
    ula uut (
        .a(a),
        .b(b),
        .op(op),
        .r(r),
        .zero(zero)
    );

    // Procedimento de teste
    initial begin
        $dumpfile("dump.vcd");
        $dumpvars(0, tb_ula);
        $display("Teste da ULA");
        $display("------------------------------");
        $display("| op  |  a  |  b  |  r  | zero |");
        $display("------------------------------");

        // Teste: Soma (op = 000)
        a = 4'd3; b = 4'd2; op = 3'b000;
        #1 $display("| %b | %2d | %2d | %2d |   %b   |", op, a, b, r, zero);

        // Teste: Subtração (op = 001)
        a = 4'd7; b = 4'd5; op = 3'b001;
        #1 $display("| %b | %2d | %2d | %2d |   %b   |", op, a, b, r, zero);

        // Teste: AND (op = 010)
        a = 4'b1100; b = 4'b1010; op = 3'b010;
        #1 $display("| %b | %b | %b | %b |   %b   |", op, a, b, r, zero);

        // Teste: OR (op = 011)
        a = 4'b0101; b = 4'b0011; op = 3'b011;
        #1 $display("| %b | %b | %b | %b |   %b   |", op, a, b, r, zero);

        // Teste: XOR (op = 100)
        a = 4'b1111; b = 4'b0101; op = 3'b100;
        #1 $display("| %b | %b | %b | %b |   %b   |", op, a, b, r, zero);

        // Teste: Igualdade (op = 101), iguais
        a = 4'd9; b = 4'd9; op = 3'b101;
        #1 $display("| %b | %2d | %2d | %b |   %b   |", op, a, b, r, zero);

        // Teste: Igualdade (op = 101), diferentes
        a = 4'd9; b = 4'd8; op = 3'b101;
        #1 $display("| %b | %2d | %2d | %b |   %b   |", op, a, b, r, zero);

        // Teste: Operação inválida (default)
        a = 4'd1; b = 4'd1; op = 3'b111;
        #1 $display("| %b | %2d | %2d | %2d |   %b   |", op, a, b, r, zero);

        $display("------------------------------");
        $finish;
    end
endmodule

dump.vcd
$date
	Wed Aug 06 16:14:08 2025
$end
$version
	Icarus Verilog
$end
$timescale
	1s
$end
$scope module tb_ula $end
$var wire 1 ! zero $end
$var wire 4 " r [3:0] $end
$var reg 4 # a [3:0] $end
$var reg 4 $ b [3:0] $end
$var reg 3 % op [2:0] $end
$scope module uut $end
$var wire 4 & a [3:0] $end
$var wire 4 ' b [3:0] $end
$var wire 3 ( op [2:0] $end
$var wire 1 ! zero $end
$var reg 4 ) r [3:0] $end
$upscope $end
$upscope $end
$enddefinitions $end
$comment Show the parameter values. $end
$dumpall
$end
#0
$dumpvars
b101 )
b0 (
b10 '
b11 &
b0 %
b10 $
b11 #
b101 "
0!
$end
#1
b10 "
b10 )
b1 %
b1 (
b101 $
b101 '
b111 #
b111 &
#2
b1000 "
b1000 )
b10 %
b10 (
b1010 $
b1010 '
b1100 #
b1100 &
#3
b111 "
b111 )
b11 %
b11 (
b11 $
b11 '
b101 #
b101 &
#4
b1010 "
b1010 )
b100 %
b100 (
b101 $
b101 '
b1111 #
b1111 &
#5
b1 "
b1 )
b101 %
b101 (
b1001 $
b1001 '
b1001 #
b1001 &
#6
1!
b0 "
b0 )
b1000 $
b1000 '
#7
b111 %
b111 (
b1 $
b1 '
b1 #
b1 &
