maquinas_estados/mealy/teste1.sv
module edge_dec(
    input logic clk, rst, level,
    output logic tick
);

typedef enum {zero, one} state_type;
state_type state_next, state_reg;

always_ff @(posedge clk, posedge rst) begin
    if(rst)
        state_reg <= zero;
    else
        state_reg <= state_next; 
end

always_comb begin
    state_next = state_reg;
    tick = 1'b1;
    case (state_reg)
        zero:
            if(level) begin
                state_next = one;
                tick = 1'b1;
            end
        one:
            if(~one)
                state_next = zero;
            default: state_next = zero;
    endcase
end
endmodule

maquinas_estados/mealy/tb_teste1.sv
module tb_edge;

logic clk, rst, level, tick;
localparam T = 20;

edge_dec uut(.*);

always begin
clk = 1'b0;
# (T/2);
clk = 1'b1;
# (T/2);
end

initial begin
rst = 1'b1;
# (T);
rst = 1'b0;
end

initial
begin
    $dumpfile("waveform.vcd");
    $dumpvars(0, tb_edge);
    level = 0;
    repeat(20) begin
        @(negedge clk);
        @(negedge clk);
        level = 1;
        @(negedge clk);
        level = 0;
    end
    $finish;
end

endmodule

maquinas_estados/mealy/waveform.vcd
$date
	Wed Aug 20 16:30:59 2025
$end
$version
	Icarus Verilog
$end
$timescale
	1s
$end
$scope module tb_edge $end
$var wire 1 ! tick $end
$var parameter 32 " T $end
$var reg 1 # clk $end
$var reg 1 $ level $end
$var reg 1 % rst $end
$scope module uut $end
$var wire 1 # clk $end
$var wire 1 $ level $end
$var wire 1 % rst $end
$var reg 1 ! tick $end
$var integer 32 & state_next [31:0] $end
$var integer 32 ' state_reg [31:0] $end
$upscope $end
$upscope $end
$enddefinitions $end
$comment Show the parameter values. $end
$dumpall
b10100 "
$end
#0
$dumpvars
b0 '
b0 &
1%
0$
0#
1!
$end
#10
1#
#20
0#
0%
#30
1#
#40
b1 &
1$
0#
#50
b0 &
b1 '
1#
#60
b0 &
0$
0#
#70
b0 '
1#
#80
0#
#90
1#
#100
b1 &
1$
0#
#110
b0 &
b1 '
1#
#120
b0 &
0$
0#
#130
b0 '
1#
#140
0#
#150
1#
#160
b1 &
1$
0#
#170
b0 &
b1 '
1#
#180
b0 &
0$
0#
#190
b0 '
1#
#200
0#
#210
1#
#220
b1 &
1$
0#
#230
b0 &
b1 '
1#
#240
b0 &
0$
0#
#250
b0 '
1#
#260
0#
#270
1#
#280
b1 &
1$
0#
#290
b0 &
b1 '
1#
#300
b0 &
0$
0#
#310
b0 '
1#
#320
0#
#330
1#
#340
b1 &
1$
0#
#350
b0 &
b1 '
1#
#360
b0 &
0$
0#
#370
b0 '
1#
#380
0#
#390
1#
#400
b1 &
1$
0#
#410
b0 &
b1 '
1#
#420
b0 &
0$
0#
#430
b0 '
1#
#440
0#
#450
1#
#460
b1 &
1$
0#
#470
b0 &
b1 '
1#
#480
b0 &
0$
0#
#490
b0 '
1#
#500
0#
#510
1#
#520
b1 &
1$
0#
#530
b0 &
b1 '
1#
#540
b0 &
0$
0#
#550
b0 '
1#
#560
0#
#570
1#
#580
b1 &
1$
0#
#590
b0 &
b1 '
1#
#600
b0 &
0$
0#
#610
b0 '
1#
#620
0#
#630
1#
#640
b1 &
1$
0#
#650
b0 &
b1 '
1#
#660
b0 &
0$
0#
#670
b0 '
1#
#680
0#
#690
1#
#700
b1 &
1$
0#
#710
b0 &
b1 '
1#
#720
b0 &
0$
0#
#730
b0 '
1#
#740
0#
#750
1#
#760
b1 &
1$
0#
#770
b0 &
b1 '
1#
#780
b0 &
0$
0#
#790
b0 '
1#
#800
0#
#810
1#
#820
b1 &
1$
0#
#830
b0 &
b1 '
1#
#840
b0 &
0$
0#
#850
b0 '
1#
#860
0#
#870
1#
#880
b1 &
1$
0#
#890
b0 &
b1 '
1#
#900
b0 &
0$
0#
#910
b0 '
1#
#920
0#
#930
1#
#940
b1 &
1$
0#
#950
b0 &
b1 '
1#
#960
b0 &
0$
0#
#970
b0 '
1#
#980
0#
#990
1#
#1000
b1 &
1$
0#
#1010
b0 &
b1 '
1#
#1020
b0 &
0$
0#
#1030
b0 '
1#
#1040
0#
#1050
1#
#1060
b1 &
1$
0#
#1070
b0 &
b1 '
1#
#1080
b0 &
0$
0#
#1090
b0 '
1#
#1100
0#
#1110
1#
#1120
b1 &
1$
0#
#1130
b0 &
b1 '
1#
#1140
b0 &
0$
0#
#1150
b0 '
1#
#1160
0#
#1170
1#
#1180
b1 &
1$
0#
#1190
b0 &
b1 '
1#
#1200
b0 &
0$
0#
