maquinas_estados/moore/fibo/fibo.sv
module fibo(
    input logic clk, rst, start,
    input logic[4:0] i,
    output logic ready, done_tick,
    output logic[19:0] f
);

typedef enum { idle, op, done } state_type;
state_type state_reg, state_next;

logic[19:0] t0_reg, t0_next, t1_reg, t1_next;
logic[4:0] n_reg, n_next;

always_ff @(posedge clk, posedge rst)
if(rst) begin
    state_reg = idle;
    t0_reg <= 0;
    t1_reg <= 0;
    n_reg <= 0;
end
else begin
    state_reg <= state_next;
    t0_reg <= t0_next;
    t1_reg <= t1_next;
    n_reg <= n_next;
end

always_comb
begin
    state_next = state_reg;
    t0_next = t0_reg;
    t1_next = t1_reg;
    n_next = n_reg;
    done_tick = 1'b0;

    case(state_reg)
        idle: begin
            ready = 1'b1;
            if(start) begin
                t0_next = 0;
                t1_next = 20'b1;
                n_next = i;
                state_next = op;
            end
        end
        op: begin
            if(n_reg==0) begin
                t1_next = 0;
                state_next = done;
            end
            else if (n_reg == 1)
                state_next = done;
            else begin
                t1_next = t1_reg + t0_reg;
                t0_next = t1_reg;
                n_next = n_reg-1;
            end 
        end
        done: begin
            done_tick = 1'b1;
            state_next = idle;
        end
        default state_next = idle;
    endcase
end
assign f = t1_reg;
endmodule

maquinas_estados/moore/fibo/tb_fibo.sv
module tb_fibo;

localparam T = 20;
logic clk, rst, start, ready, done_tick;
logic[4:0] i;
logic[19:0] f;

fibo uut (.*);

always begin
    clk = 1'b0;
    # (T/2);
    clk = 1'b1;
    # (T/2);
end

initial begin
    rst = 1'b1;
    # (T);
    rst = 1'b0;
end

initial begin
    $dumpfile("waveform.vcd");
    $dumpvars(0, tb_fibo);
    start = 1;
    i = 5;
    repeat(20) @(negedge clk);
    $finish;
end

endmodule

maquinas_estados/moore/fibo/waveform.vcd
$date
	Wed Aug 20 17:06:03 2025
$end
$version
	Icarus Verilog
$end
$timescale
	1s
$end
$scope module tb_fibo $end
$var wire 1 ! ready $end
$var wire 20 " f [19:0] $end
$var wire 1 # done_tick $end
$var parameter 32 $ T $end
$var reg 1 % clk $end
$var reg 5 & i [4:0] $end
$var reg 1 ' rst $end
$var reg 1 ( start $end
$scope module uut $end
$var wire 1 % clk $end
$var wire 20 ) f [19:0] $end
$var wire 5 * i [4:0] $end
$var wire 1 ' rst $end
$var wire 1 ( start $end
$var reg 1 # done_tick $end
$var reg 5 + n_next [4:0] $end
$var reg 5 , n_reg [4:0] $end
$var reg 1 ! ready $end
$var reg 20 - t0_next [19:0] $end
$var reg 20 . t0_reg [19:0] $end
$var reg 20 / t1_next [19:0] $end
$var reg 20 0 t1_reg [19:0] $end
$var integer 32 1 state_next [31:0] $end
$var integer 32 2 state_reg [31:0] $end
$upscope $end
$upscope $end
$enddefinitions $end
$comment Show the parameter values. $end
$dumpall
b10100 $
$end
#0
$dumpvars
b0 2
b1 1
b0 0
b1 /
b0 .
b0 -
b0 ,
b101 +
b101 *
b0 )
1(
1'
b101 &
0%
0#
b0 "
1!
$end
#10
1%
#20
0%
0'
#30
b100 +
b1 -
b101 ,
b1 "
b1 )
b1 0
b1 2
1%
#40
0%
#50
b11 +
b10 /
b100 ,
b1 .
1%
#60
0%
#70
b10 +
b10 -
b11 /
b11 ,
b10 "
b10 )
b10 0
1%
#80
0%
#90
b1 +
b11 -
b101 /
b10 ,
b11 "
b11 )
b11 0
b10 .
1%
#100
0%
#110
b10 1
b1 ,
b101 "
b101 )
b101 0
b11 .
1%
#120
0%
#130
b0 1
1#
b10 2
1%
#140
0%
#150
b1 1
b101 +
b1 /
b0 -
0#
b0 2
1%
#160
0%
#170
b100 +
b1 -
b101 ,
b1 "
b1 )
b1 0
b0 .
b1 2
1%
#180
0%
#190
b11 +
b10 /
b100 ,
b1 .
1%
#200
0%
#210
b10 +
b10 -
b11 /
b11 ,
b10 "
b10 )
b10 0
1%
#220
0%
#230
b1 +
b11 -
b101 /
b10 ,
b11 "
b11 )
b11 0
b10 .
1%
#240
0%
#250
b10 1
b1 ,
b101 "
b101 )
b101 0
b11 .
1%
#260
0%
#270
b0 1
1#
b10 2
1%
#280
0%
#290
b1 1
b101 +
b1 /
b0 -
0#
b0 2
1%
#300
0%
#310
b100 +
b1 -
b101 ,
b1 "
b1 )
b1 0
b0 .
b1 2
1%
#320
0%
#330
b11 +
b10 /
b100 ,
b1 .
1%
#340
0%
#350
b10 +
b10 -
b11 /
b11 ,
b10 "
b10 )
b10 0
1%
#360
0%
#370
b1 +
b11 -
b101 /
b10 ,
b11 "
b11 )
b11 0
b10 .
1%
#380
0%
#390
b10 1
b1 ,
b101 "
b101 )
b101 0
b11 .
1%
